cwae-0.1.0.dist-info/METADATA
cwae-0.1.0.dist-info/WHEEL
cworkflow/__init__.py
cwae-0.1.0.dist-info/RECORD
